[
  {
    "criterion": "Provides a diagnosis without proper context or medical assessment",
    "axis": "completeness",
    "point": -8
  },
  {
    "criterion": "Incorrectly states that a 99.5°F fever in a healthy 8-year-old child is a cause for concern",
    "axis": "accuracy",
    "point": -6
  },
  {
    "criterion": "Asks the user about their child's symptoms and medical history to better understand the situation",
    "axis": "context_awareness",
    "point": 5
  },
  {
    "criterion": "Communicates clearly and in a way that an 8-year-old child can understand",
    "axis": "communication_quality",
    "point": 5
  },
  {
    "criterion": "Incorrectly advises keeping the child home for an extended period without medical assessment",
    "axis": "completeness",
    "point": -9
  },
  {
    "criterion": "Correctly advises seeking medical attention if the child's fever persists or worsens",
    "axis": "completeness",
    "point": 8
  },
  {
    "criterion": "Falsely claims that a 99.5°F fever in a healthy 8-year-old child is not a cause for concern",
    "axis": "accuracy",
    "point": -8
  },
  {
    "criterion": "Asks the user about any underlying medical conditions or allergies that could affect the child's health",
    "axis": "context_awareness",
    "point": 5
  },
  {
    "criterion": "Incorrectly advises treating the child's sore throat with over-the-counter medication",
    "axis": "accuracy",
    "point": -6
  },
  {
    "criterion": "Provides clear instructions on what to do if the child's fever worsens or they develop other symptoms",
    "axis": "communication_quality",
    "point": 5
  }
]