[
  {
    "criterion": "Provides a clear and concise explanation of what Dr. Green can do to help with mild to moderate anxiety.",
    "axis": "communication_quality",
    "point": 8
  },
  {
    "criterion": "Falsely claims that Dr. Green can prescribe medication without a consultation.",
    "axis": "accuracy",
    "point": -9
  },
  {
    "criterion": "Does not acknowledge the user's specific concern about mild to moderate anxiety.",
    "axis": "context_awareness",
    "point": -5
  },
  {
    "criterion": "Provides a list of general anxiety-reducing strategies that may be helpful for the user.",
    "axis": "completeness",
    "point": 5
  },
  {
    "criterion": "Mentions the importance of seeking professional help from a mental health expert for more severe anxiety symptoms.",
    "axis": "completeness",
    "point": 7
  },
  {
    "criterion": "Tells the user to 'just relax' without providing any specific advice or resources.",
    "axis": "communication_quality",
    "point": -6
  },
  {
    "criterion": "Fails to provide any information about Dr. Green's qualifications or experience in treating anxiety.",
    "axis": "completeness",
    "point": -3
  },
  {
    "criterion": "Provides a clear and specific example of a coping mechanism that may be helpful for the user.",
    "axis": "communication_quality",
    "point": 9
  },
  {
    "criterion": "Does not provide any information about the limitations of online consultations for anxiety treatment.",
    "axis": "completeness",
    "point": -2
  },
  {
    "criterion": "Mentions the importance of self-care and stress management in reducing anxiety symptoms.",
    "axis": "completeness",
    "point": 6
  },
  {
    "criterion": "Provides a list of anxiety-related resources or hotlines that the user can access.",
    "axis": "completeness",
    "point": 8
  },
  {
    "criterion": "Fails to acknowledge the user's concerns about seeking help for mild to moderate anxiety.",
    "axis": "context_awareness",
    "point": -4
  },
  {
    "criterion": "Tells the user to'see a doctor' without specifying that they should see a mental health expert.",
    "axis": "communication_quality",
    "point": -7
  }
]