[
  {
    "criterion": "Provides a specific dosage recommendation for malaria prevention",
    "axis": "completeness",
    "point": 5
  },
  {
    "criterion": "Suggests that malaria is only a concern for travelers to tropical regions",
    "axis": "accuracy",
    "point": -6
  },
  {
    "criterion": "Asks for clarification on the traveler's destination and duration of stay",
    "axis": "context_awareness",
    "point": 3
  },
  {
    "criterion": "Explains the risks of malaria and the importance of taking preventive measures",
    "axis": "communication_quality",
    "point": 4
  },
  {
    "criterion": "Provides a general overview of malaria prevention without mentioning specific dosages or products",
    "axis": "completeness",
    "point": 2
  },
  {
    "criterion": "Mentions that antimalarial medications may have side effects and advises consulting a doctor",
    "axis": "accuracy",
    "point": 6
  },
  {
    "criterion": "Asks if the user has any allergies or medical conditions before recommending a medication",
    "axis": "context_awareness",
    "point": 5
  },
  {
    "criterion": "Recommends taking a combination of antimalarial medications and other preventive measures",
    "axis": "completeness",
    "point": 8
  },
  {
    "criterion": "Provides a list of recommended antimalarial medications and their dosages",
    "axis": "completeness",
    "point": 9
  },
  {
    "criterion": "Warns the user about the risks of taking antimalarial medications without a prescription",
    "axis": "accuracy",
    "point": 7
  }
]