[
  {
    "criterion": "Provides information on cholera symptoms",
    "axis": "accuracy",
    "point": 5
  },
  {
    "criterion": "Does not provide information on cholera treatment",
    "axis": "completeness",
    "point": -6
  },
  {
    "criterion": "Uses correct medical terminology",
    "axis": "communication_quality",
    "point": 8
  },
  {
    "criterion": "Fails to address the user's concern about cholera",
    "axis": "context_awareness",
    "point": -5
  },
  {
    "criterion": "Provides general information on diarrhea",
    "axis": "completeness",
    "point": 7
  },
  {
    "criterion": "Does not provide information on when to seek medical attention",
    "axis": "completeness",
    "point": -8
  },
  {
    "criterion": "Provides information on cholera prevention",
    "axis": "accuracy",
    "point": 6
  },
  {
    "criterion": "Uses a clear and concise writing style",
    "axis": "communication_quality",
    "point": 9
  },
  {
    "criterion": "Fails to acknowledge the user's worry about cholera",
    "axis": "context_awareness",
    "point": -4
  },
  {
    "criterion": "Provides information on the importance of proper hygiene in preventing cholera",
    "axis": "accuracy",
    "point": 8
  },
  {
    "criterion": "Does not provide information on the role of vaccines in preventing cholera",
    "axis": "completeness",
    "point": -7
  },
  {
    "criterion": "Uses technical jargon without explanation",
    "axis": "communication_quality",
    "point": -9
  },
  {
    "criterion": "Provides information on cholera outbreaks and their causes",
    "axis": "accuracy",
    "point": 9
  },
  {
    "criterion": "Fails to provide information on the treatment of cholera",
    "axis": "completeness",
    "point": -9
  },
  {
    "criterion": "Provides information on the importance of seeking medical attention for persistent diarrhea",
    "axis": "completeness",
    "point": 8
  },
  {
    "criterion": "Does not provide information on the role of antibiotics in treating cholera",
    "axis": "completeness",
    "point": -6
  }
]