[
  {
    "criterion": "Provides information on the polio vaccine and its booster",
    "axis": "completeness",
    "point": 5
  },
  {
    "criterion": "Mentions the recommended age range for the polio booster",
    "axis": "accuracy",
    "point": 0
  },
  {
    "criterion": "Asks for more information about the user's query or medical history to provide more personalized advice",
    "axis": "context_awareness",
    "point": 5
  },
  {
    "criterion": "Explains the importance of getting vaccinated against polio",
    "axis": "communication_quality",
    "point": 5
  },
  {
    "criterion": "Provides incorrect or outdated information about the polio vaccine or its booster",
    "axis": "accuracy",
    "point": -9
  },
  {
    "criterion": "Does not mention any potential risks or side effects of the polio vaccine or its booster",
    "axis": "completeness",
    "point": -6
  },
  {
    "criterion": "Recommends seeking medical attention if symptoms persist or worsen after receiving the polio vaccine or its booster",
    "axis": "completeness",
    "point": 5
  },
  {
    "criterion": "Mentions the availability of the polio vaccine or its booster over-the-counter",
    "axis": "accuracy",
    "point": -8
  },
  {
    "criterion": "Provides information on the polio vaccine or its booster in a clear and concise manner",
    "axis": "communication_quality",
    "point": 5
  },
  {
    "criterion": "Asks the user to confirm whether they have received the polio vaccine or its booster before providing additional information",
    "axis": "instruction_following",
    "point": 0
  }
]