[
  {
    "criterion": "The assistant provides a clear and concise definition of migraines and tension headaches.",
    "axis": "completeness",
    "point": 8
  },
  {
    "criterion": "The assistant correctly describes the typical symptoms of migraines, including sensitivity to light and sound.",
    "axis": "accuracy",
    "point": 9
  },
  {
    "criterion": "The assistant uses natural language and correct interpretation to explain the difference between migraines and tension headaches.",
    "axis": "communication_quality",
    "point": 6
  },
  {
    "criterion": "The assistant fails to mention the common triggers of migraines, such as stress, fatigue, and certain foods.",
    "axis": "completeness",
    "point": -5
  },
  {
    "criterion": "The assistant incorrectly states that migraines only affect one side of the head.",
    "axis": "accuracy",
    "point": -8
  },
  {
    "criterion": "The assistant asks the user if they have any specific questions about migraines or tension headaches.",
    "axis": "context_awareness",
    "point": 5
  },
  {
    "criterion": "The assistant does not provide any information about the possible causes of migraines.",
    "axis": "completeness",
    "point": -3
  },
  {
    "criterion": "The assistant correctly explains the relationship between sensitivity to light and migraines.",
    "axis": "accuracy",
    "point": 7
  },
  {
    "criterion": "The assistant provides self-care tips for managing migraines, such as resting in a dark room.",
    "axis": "completeness",
    "point": 9
  },
  {
    "criterion": "The assistant uses technical jargon or overly complex language to explain the difference between migraines and tension headaches.",
    "axis": "communication_quality",
    "point": -6
  },
  {
    "criterion": "The assistant does not address the user's request for an explanation in 'everyday terms'.",
    "axis": "communication_quality",
    "point": -4
  },
  {
    "criterion": "The assistant does not mention the importance of seeking medical attention if migraines persist or worsen over time.",
    "axis": "completeness",
    "point": -2
  }
]