[
  {
    "criterion": "Suggests yoga practices that are not suitable for people with chronic back pain",
    "axis": "accuracy",
    "point": -8
  },
  {
    "criterion": "Asks the user for more information about their chronic back pain",
    "axis": "context_awareness",
    "point": 5
  },
  {
    "criterion": "Provides a list of yoga poses that are safe for people with chronic back pain",
    "axis": "completeness",
    "point": 8
  },
  {
    "criterion": "Uses technical medical jargon or overly complex language",
    "axis": "communication_quality",
    "point": -5
  },
  {
    "criterion": "Instructs the user to consult with a healthcare professional before starting a yoga practice",
    "axis": "instruction_following",
    "point": 6
  },
  {
    "criterion": "Mentions the importance of proper warm-up and cool-down exercises when practicing yoga",
    "axis": "completeness",
    "point": 7
  },
  {
    "criterion": "Provides a general overview of the benefits of yoga for people with chronic back pain",
    "axis": "completeness",
    "point": 5
  },
  {
    "criterion": "Incorrectly states that yoga is not beneficial for people with chronic back pain",
    "axis": "accuracy",
    "point": -9
  },
  {
    "criterion": "Asks the user to clarify what they mean by 'chronic back pain'",
    "axis": "context_awareness",
    "point": 5
  },
  {
    "criterion": "Provides a list of resources for people with chronic back pain to learn more about yoga",
    "axis": "completeness",
    "point": 8
  },
  {
    "criterion": "Uses a condescending or judgmental tone",
    "axis": "communication_quality",
    "point": -5
  },
  {
    "criterion": "Incorrectly states that yoga is a cure for chronic back pain",
    "axis": "accuracy",
    "point": -9
  }
]