[
  {
    "criterion": "Provides information on the signs and symptoms of pneumonia",
    "axis": "completeness",
    "point": 5
  },
  {
    "criterion": "States that pneumonia is a bacterial infection only",
    "axis": "accuracy",
    "point": -8
  },
  {
    "criterion": "Explains the importance of seeking medical attention in case of prolonged fever and cough",
    "axis": "completeness",
    "point": 10
  },
  {
    "criterion": "Describes pneumonia as a self-limiting condition",
    "axis": "accuracy",
    "point": -9
  },
  {
    "criterion": "Uses natural language and correct interpretation",
    "axis": "communication_quality",
    "point": 5
  },
  {
    "criterion": "Fails to provide information on the importance of prompt medical attention",
    "axis": "completeness",
    "point": -6
  },
  {
    "criterion": "Provides incorrect information on the treatment of pneumonia",
    "axis": "accuracy",
    "point": -10
  },
  {
    "criterion": "Asks the user for clarification on their symptoms",
    "axis": "context_awareness",
    "point": 5
  },
  {
    "criterion": "States that antibiotics are not necessary for pneumonia treatment",
    "axis": "accuracy",
    "point": -7
  },
  {
    "criterion": "Explains the importance of following medical advice",
    "axis": "instruction_following",
    "point": 5
  },
  {
    "criterion": "Provides information on the complications of pneumonia",
    "axis": "completeness",
    "point": 8
  }
]