[
  {
    "criterion": "Provides a list of recommended daily sunscreen usage times of day.",
    "axis": "completeness",
    "point": 5
  },
  {
    "criterion": "States that sunscreen should only be applied before going outside.",
    "axis": "accuracy",
    "point": -6
  },
  {
    "criterion": "Asks the user about their current sunscreen usage habits to provide more personalized advice.",
    "axis": "context_awareness",
    "point": 5
  },
  {
    "criterion": "Uses technical jargon or complex medical terminology in the response.",
    "axis": "communication_quality",
    "point": -8
  },
  {
    "criterion": "Suggests using a physical barrier, such as clothing or shade, in addition to sunscreen for overall skin protection.",
    "axis": "completeness",
    "point": 8
  },
  {
    "criterion": "Incorrectly states that sunscreen is only necessary for people with fair skin.",
    "axis": "accuracy",
    "point": -9
  },
  {
    "criterion": "Provides a clear explanation of the importance of reapplying sunscreen after swimming or sweating.",
    "axis": "communication_quality",
    "point": 7
  },
  {
    "criterion": "Fails to mention that sunscreen should be reapplied every 2 hours or immediately after swimming or sweating.",
    "axis": "completeness",
    "point": -5
  },
  {
    "criterion": "Recommends using a broad-spectrum sunscreen with at least SPF 30.",
    "axis": "completeness",
    "point": 9
  },
  {
    "criterion": "States that sunscreen is the only effective way to protect skin from the sun.",
    "axis": "accuracy",
    "point": -7
  }
]