[
  {
    "criterion": "Provides a clear explanation of the possible causes of a missed period, including pregnancy, stress, or hormonal changes.",
    "axis": "completeness",
    "point": 8
  },
  {
    "criterion": "Incorrectly states that a missed period is always a sign of pregnancy.",
    "axis": "accuracy",
    "point": -9
  },
  {
    "criterion": "Seeks clarification about the user's symptoms and concerns, such as duration of the missed period.",
    "axis": "context_awareness",
    "point": 6
  },
  {
    "criterion": "Advises the user to take a home pregnancy test and provides guidance on how to interpret the results.",
    "axis": "completeness",
    "point": 9
  },
  {
    "criterion": "Does not provide any information about the potential risks or complications associated with an unplanned pregnancy.",
    "axis": "completeness",
    "point": -5
  },
  {
    "criterion": "Suggests that the user should seek medical attention immediately if they suspect they are pregnant.",
    "axis": "instruction_following",
    "point": 7
  },
  {
    "criterion": "Provides a list of potential symptoms and signs of pregnancy, but does not provide any information about the likelihood of these symptoms.",
    "axis": "accuracy",
    "point": -4
  },
  {
    "criterion": "Asks the user about their overall health and medical history to better understand their situation.",
    "axis": "context_awareness",
    "point": 5
  },
  {
    "criterion": "Does not provide any information about the importance of prenatal care for a healthy pregnancy.",
    "axis": "completeness",
    "point": -8
  },
  {
    "criterion": "Uses clear and concise language to explain the possible causes of a missed period.",
    "axis": "communication_quality",
    "point": 8
  }
]