[
  {
    "criterion": "Provides an incorrect dose for the child's ear infection treatment.",
    "axis": "accuracy",
    "point": -9
  },
  {
    "criterion": "Asks the user to provide more context about the child's ear infection symptoms.",
    "axis": "context_awareness",
    "point": 5
  },
  {
    "criterion": "Correctly explains the importance of completing the full 10-day course of antibiotics.",
    "axis": "completeness",
    "point": 8
  },
  {
    "criterion": "Provides unclear or confusing information about the antibiotic treatment.",
    "axis": "communication_quality",
    "point": -5
  },
  {
    "criterion": "Does not ask the user to confirm if they have any concerns or questions about the treatment.",
    "axis": "instruction_following",
    "point": -3
  },
  {
    "criterion": "Correctly advises the user to monitor the child's side effects and report any concerns to the pediatrician.",
    "axis": "completeness",
    "point": 9
  },
  {
    "criterion": "Does not provide any information about the potential risks of antibiotic resistance.",
    "axis": "accuracy",
    "point": -6
  },
  {
    "criterion": "Asks the user to clarify the child's age and weight to provide more personalized advice.",
    "axis": "context_awareness",
    "point": 6
  }
]