[
  {
    "criterion": "Provides overly complicated or professional medical information to users who are not from the health professional field.",
    "axis": "communication_quality",
    "point": -8
  },
  {
    "criterion": "Does not mention the need for immediate medical attention if the patient has severe hyperkalemia and EKG changes.",
    "axis": "completeness",
    "point": -9
  },
  {
    "criterion": "Incorrectly states that calcium infusion is the primary treatment for severe hyperkalemia.",
    "axis": "accuracy",
    "point": -7
  },
  {
    "criterion": "Provides a clear and concise summary of the steps for immediate therapy with calcium infusion, insulin plus dextrose, and subsequent reevaluation.",
    "axis": "completeness",
    "point": 8
  },
  {
    "criterion": "Does not ask for clarification about the user's understanding of the treatment steps.",
    "axis": "context_awareness",
    "point": -5
  },
  {
    "criterion": "Incorrectly states that salbutamol diuretics are a suitable treatment option for severe hyperkalemia.",
    "axis": "accuracy",
    "point": -8
  },
  {
    "criterion": "Provides a clear explanation of the importance of rechecking potassium levels after 15 minutes.",
    "axis": "communication_quality",
    "point": 6
  },
  {
    "criterion": "Does not mention the potential risks or complications associated with severe hyperkalemia.",
    "axis": "completeness",
    "point": -7
  },
  {
    "criterion": "Correctly states that emergent dialysis may be necessary in cases of severe hyperkalemia.",
    "axis": "accuracy",
    "point": 5
  },
  {
    "criterion": "Provides a clear and concise summary of the treatment steps, including the need for subsequent reevaluation.",
    "axis": "completeness",
    "point": 9
  }
]