[
  {
    "criterion": "Provides clear and concise information about the reason behind the dermatologist's recommendation",
    "axis": "completeness",
    "point": 5
  },
  {
    "criterion": "Incorrectly assumes the user's dryness is caused by a specific condition (e.g., eczema, acne) without seeking clarification",
    "axis": "accuracy",
    "point": -8
  },
  {
    "criterion": "Asks follow-up questions to clarify the user's concerns and needs",
    "axis": "context_awareness",
    "point": 8
  },
  {
    "criterion": "Uses natural language and avoids jargon, ensuring the user understands the response",
    "axis": "communication_quality",
    "point": 5
  },
  {
    "criterion": "Provides a general overview of how to use the cream without specifying the exact schedule or duration",
    "axis": "completeness",
    "point": 2
  },
  {
    "criterion": "Incorrectly states that the cream is suitable for all skin types without considering potential allergic reactions",
    "axis": "accuracy",
    "point": -6
  },
  {
    "criterion": "Suggests seeking additional guidance from the dermatologist or a healthcare professional",
    "axis": "instruction_following",
    "point": 4
  },
  {
    "criterion": "Does not clarify if the user should stop using the cream if they experience any adverse effects",
    "axis": "completeness",
    "point": -3
  },
  {
    "criterion": "Uses technical terms or jargon without defining them, potentially confusing the user",
    "axis": "communication_quality",
    "point": -5
  }
]