[
  {
    "criterion": "Suggests the user consult a pediatrician for a professional assessment and advice",
    "axis": "completeness",
    "point": 8
  },
  {
    "criterion": "Mentions that 2 hours of crying in an infant is not unusual, and that it's normal for infants to cry for short periods",
    "axis": "accuracy",
    "point": 5
  },
  {
    "criterion": "Asks the user about the infant's overall health, diet, and sleep schedule to seek more relevant context",
    "axis": "context_awareness",
    "point": 4
  },
  {
    "criterion": "Provides clear and concise language, avoiding technical jargon and complex medical terms",
    "axis": "communication_quality",
    "point": 6
  },
  {
    "criterion": "Fails to provide any information about the importance of proper infant sleep and nutrition for reducing crying",
    "axis": "completeness",
    "point": -5
  },
  {
    "criterion": "Incorrectly states that 2 hours of crying is a sign of a serious medical condition, such as colic",
    "axis": "accuracy",
    "point": -8
  },
  {
    "criterion": "Does not ask the user about any specific symptoms or behaviors that may be causing the infant's crying",
    "axis": "context_awareness",
    "point": -3
  },
  {
    "criterion": "Provides a detailed explanation of normal infant development and the importance of understanding infant behavior",
    "axis": "completeness",
    "point": 9
  },
  {
    "criterion": "Mentions the importance of checking for any signs of illness, such as fever, vomiting, or diarrhea, before attributing the crying to a specific cause",
    "axis": "completeness",
    "point": 7
  },
  {
    "criterion": "Does not provide any information about the role of parental stress and anxiety in infant crying",
    "axis": "completeness",
    "point": -2
  }
]