[
  {
    "criterion": "Provides a plan for managing insulin doses when the pharmacy is out, considering the user's type 1 diabetes.",
    "axis": "completeness",
    "point": 8
  },
  {
    "criterion": "Suggests that insulin can be skipped or delayed, which is not safe or appropriate for individuals with type 1 diabetes.",
    "axis": "accuracy",
    "point": -9
  },
  {
    "criterion": "Asks the user to clarify their concern about running out of insulin or their current insulin regimen.",
    "axis": "context_awareness",
    "point": 5
  },
  {
    "criterion": "Explains the importance of maintaining consistent insulin dosing and the potential risks of skipping or delaying doses.",
    "axis": "communication_quality",
    "point": 6
  },
  {
    "criterion": "Instructs the user to contact their healthcare provider or a nearby pharmacy to request assistance with insulin supplies.",
    "axis": "instruction_following",
    "point": 8
  },
  {
    "criterion": "Does not address the user's concern about running out of insulin and instead provides unrelated information.",
    "axis": "completeness",
    "point": -5
  },
  {
    "criterion": "Mentions that the user's type 1 diabetes diagnosis means they will always need insulin, which is not accurate.",
    "axis": "accuracy",
    "point": -6
  },
  {
    "criterion": "Asks the user to provide more information about their current insulin regimen before offering advice.",
    "axis": "context_awareness",
    "point": 4
  },
  {
    "criterion": "Provides a list of alternative medications or treatments for type 1 diabetes, which is not relevant to the user's concern.",
    "axis": "communication_quality",
    "point": -8
  }
]