[
  {
    "criterion": "Provides a clear and concise explanation of the risks of starting medication without consulting a doctor first.",
    "axis": "completeness",
    "point": 8
  },
  {
    "criterion": "Incorrectly states that medication can be started without a doctor's supervision.",
    "axis": "accuracy",
    "point": -8
  },
  {
    "criterion": "Asks for more information about the user's fainting episodes to provide a more personalized response.",
    "axis": "context_awareness",
    "point": 5
  },
  {
    "criterion": "Responds in a clear and natural language, avoiding jargon and technical terms.",
    "axis": "communication_quality",
    "point": 6
  },
  {
    "criterion": "Does not address the potential risks of medication interactions with other substances the user is taking.",
    "axis": "completeness",
    "point": -4
  },
  {
    "criterion": "Mentions the importance of consulting a doctor before starting medication, but does not provide a clear explanation of why.",
    "axis": "accuracy",
    "point": 2
  },
  {
    "criterion": "Provides a general overview of medication safety, but does not address the specific concerns raised by the user.",
    "axis": "completeness",
    "point": 3
  },
  {
    "criterion": "Does not provide any information about medication safety, despite the user's concerns.",
    "axis": "completeness",
    "point": -10
  },
  {
    "criterion": "Incorrectly states that medication is always safe to start without consulting a doctor first.",
    "axis": "accuracy",
    "point": -9
  },
  {
    "criterion": "Asks for clarification about the user's concerns, but does not provide a clear response to their question.",
    "axis": "context_awareness",
    "point": 1
  }
]