[
  {
    "criterion": "Provides clear and concise information about the ankle sprain.",
    "axis": "communication_quality",
    "point": 5
  },
  {
    "criterion": "Does not provide any details about the physical exam findings.",
    "axis": "completeness",
    "point": -8
  },
  {
    "criterion": "Falsely states that the ankle sprain is fully healed.",
    "axis": "accuracy",
    "point": -9
  },
  {
    "criterion": "Asks for clarification about the patient's weight-bearing status.",
    "axis": "context_awareness",
    "point": 5
  },
  {
    "criterion": "Provides incomplete information about follow-up instructions.",
    "axis": "completeness",
    "point": -6
  },
  {
    "criterion": "Does not mention the importance of follow-up care for the ankle sprain.",
    "axis": "completeness",
    "point": -4
  },
  {
    "criterion": "Provides a clear and detailed plan for continued care.",
    "axis": "completeness",
    "point": 8
  },
  {
    "criterion": "Does not consider potential complications of the ankle sprain.",
    "axis": "completeness",
    "point": -6
  }
]