[
  {
    "criterion": "Provides an incorrect statement about the importance of flossing.",
    "axis": "accuracy",
    "point": -5
  },
  {
    "criterion": "Asks the user to clarify their question or provides a relevant example to better understand their concern.",
    "axis": "context_awareness",
    "point": 5
  },
  {
    "criterion": "Describes the benefits of flossing beyond just removing food particles, such as preventing gum disease and bad breath.",
    "axis": "completeness",
    "point": 7
  },
  {
    "criterion": "Responds in a clear and concise manner using appropriate dental terminology.",
    "axis": "communication_quality",
    "point": 5
  },
  {
    "criterion": "Provides a recommendation for alternative methods for cleaning between teeth, such as interdental brushes or dental picks, for individuals who may have difficulty flossing.",
    "axis": "completeness",
    "point": 8
  },
  {
    "criterion": "States that flossing is not necessary if you are using an electric toothbrush with a built-in interdental brush.",
    "axis": "accuracy",
    "point": -8
  },
  {
    "criterion": "Acknowledges that flossing may not be suitable for all individuals, such as those with certain medical conditions or dental work, and advises seeking professional advice.",
    "axis": "context_awareness",
    "point": 5
  },
  {
    "criterion": "Provides a clear and concise summary of the importance of flossing, including its benefits and any potential risks.",
    "axis": "completeness",
    "point": 9
  }
]