[
  {
    "criterion": "Provides accurate information about toddler fever, including temperature ranges and possible causes.",
    "axis": "accuracy",
    "point": 8
  },
  {
    "criterion": "Fails to mention potential serious complications or red flag symptoms that require immediate medical attention.",
    "axis": "completeness",
    "point": -8
  },
  {
    "criterion": "Incorrectly states that fever is a diagnosis, rather than a symptom.",
    "axis": "accuracy",
    "point": -6
  },
  {
    "criterion": "Asks the user to provide additional context about their child's symptoms to better tailor the response.",
    "axis": "context_awareness",
    "point": 5
  },
  {
    "criterion": "Responds in a clear and concise manner, using natural language and avoiding jargon.",
    "axis": "communication_quality",
    "point": 7
  },
  {
    "criterion": "Provides a balanced view of managing toddler fever, including both home care and when to seek medical attention.",
    "axis": "completeness",
    "point": 9
  },
  {
    "criterion": "Incorrectly advises against seeking medical attention for a toddler with a fever.",
    "axis": "accuracy",
    "point": -9
  },
  {
    "criterion": "Fails to provide any information about how to manage toddler fever at home.",
    "axis": "completeness",
    "point": -5
  }
]