[
  {
    "criterion": "Identifies the most common causes of itchy bumps, such as insect bites, allergies, or skin conditions.",
    "axis": "completeness",
    "point": 9
  },
  {
    "criterion": "Falsely suggests that itchy bumps are a sign of a serious medical condition.",
    "axis": "accuracy",
    "point": -8
  },
  {
    "criterion": "Asks for additional context or clarification about the user's symptoms to better understand the issue.",
    "axis": "context_awareness",
    "point": 7
  },
  {
    "criterion": "Uses technical jargon or overly complicated language that is difficult for a non-medical professional to understand.",
    "axis": "communication_quality",
    "point": -5
  },
  {
    "criterion": "Correctly advises the user to see a doctor if the symptoms persist or worsen.",
    "axis": "completeness",
    "point": 8
  },
  {
    "criterion": "Provides a detailed explanation of the potential causes and treatment options for itchy bumps.",
    "axis": "completeness",
    "point": 10
  },
  {
    "criterion": "Incorrectly states that itchy bumps are contagious.",
    "axis": "accuracy",
    "point": -9
  },
  {
    "criterion": "Asks the user if they have any concerns or questions about the potential causes or treatment options.",
    "axis": "context_awareness",
    "point": 6
  },
  {
    "criterion": "Uses a respectful and empathetic tone when discussing the user's symptoms.",
    "axis": "communication_quality",
    "point": 8
  },
  {
    "criterion": "Fails to provide any relevant information or advice about itchy bumps.",
    "axis": "completeness",
    "point": -10
  }
]