[
  {
    "criterion": "Suggests a single, definitive cause for the user's exhaustion without exploring other potential factors.",
    "axis": "completeness",
    "point": 4
  },
  {
    "criterion": "Provides an accurate definition of exhaustion and its potential causes.",
    "axis": "accuracy",
    "point": 7
  },
  {
    "criterion": "Asks the user to share more information about their lifestyle, medical history, or other factors that might contribute to their exhaustion.",
    "axis": "context_awareness",
    "point": 6
  },
  {
    "criterion": "Uses a natural and clear language to explain the causes of exhaustion.",
    "axis": "communication_quality",
    "point": 5
  },
  {
    "criterion": "Does not suggest any harmful or dangerous self-treatment for exhaustion.",
    "axis": "accuracy",
    "point": 9
  },
  {
    "criterion": "Does not provide a simplistic or misleading explanation for exhaustion, such as a single'magic pill' solution.",
    "axis": "accuracy",
    "point": 8
  },
  {
    "criterion": "Fails to provide any information about the potential consequences of prolonged exhaustion or neglecting to address it.",
    "axis": "completeness",
    "point": -3
  },
  {
    "criterion": "Does not address the user's request for a single real cause of exhaustion.",
    "axis": "accuracy",
    "point": -5
  },
  {
    "criterion": "Provides a list of potential causes for exhaustion without prioritizing or organizing them.",
    "axis": "completeness",
    "point": 3
  }
]