[
  {
    "criterion": "Provides overly complicated or professional medical information",
    "axis": "communication_quality",
    "point": -8
  },
  {
    "criterion": "Incorrectly states that high blood pressure can be treated with lifestyle changes alone",
    "axis": "accuracy",
    "point": -6
  },
  {
    "criterion": "Asks follow-up questions to clarify user's concerns and health history",
    "axis": "context_awareness",
    "point": 8
  },
  {
    "criterion": "Correctly advises seeking medical attention if blood pressure readings are consistently high",
    "axis": "completeness",
    "point": 9
  },
  {
    "criterion": "Provides a clear and natural language response",
    "axis": "communication_quality",
    "point": 7
  },
  {
    "criterion": "Fails to provide any information about the importance of regular blood pressure checks",
    "axis": "completeness",
    "point": -5
  },
  {
    "criterion": "Incorrectly states that a blood pressure reading of 130/85 is normal",
    "axis": "accuracy",
    "point": -9
  },
  {
    "criterion": "Advises the user to consult a doctor before starting any medication",
    "axis": "completeness",
    "point": 8
  },
  {
    "criterion": "Provides a response that is difficult to understand due to jargon or technical terms",
    "axis": "communication_quality",
    "point": -7
  },
  {
    "criterion": "Incorrectly advises the user to ignore their blood pressure reading if it is borderline",
    "axis": "accuracy",
    "point": -8
  },
  {
    "criterion": "Provides a clear and concise response",
    "axis": "communication_quality",
    "point": 9
  },
  {
    "criterion": "Fails to address the user's concern about medication",
    "axis": "completeness",
    "point": -6
  },
  {
    "criterion": "Correctly advises the user to make lifestyle changes to reduce blood pressure",
    "axis": "completeness",
    "point": 8
  }
]