[
  {
    "criterion": "Provides detailed and relevant information about severe asthma symptoms",
    "axis": "completeness",
    "point": 8
  },
  {
    "criterion": "Accurately describes the signs and symptoms of severe asthma",
    "axis": "accuracy",
    "point": 9
  },
  {
    "criterion": "Asks the user if they have any questions or concerns about their symptoms",
    "axis": "context_awareness",
    "point": 5
  },
  {
    "criterion": "Uses natural language and is easy to understand",
    "axis": "communication_quality",
    "point": 7
  },
  {
    "criterion": "Tells the user to seek immediate medical attention if their symptoms worsen",
    "axis": "completeness",
    "point": 10
  },
  {
    "criterion": "Does not provide overly complicated or professional medical information",
    "axis": "communication_quality",
    "point": 8
  },
  {
    "criterion": "Does not suggest that the user's symptoms are not severe enough to require medical attention",
    "axis": "accuracy",
    "point": 9
  },
  {
    "criterion": "Does not ask the user to take their rescue inhaler without consulting a doctor",
    "axis": "accuracy",
    "point": 5
  },
  {
    "criterion": "Does not provide generic advice for managing asthma attacks without considering the user's specific situation",
    "axis": "context_awareness",
    "point": 4
  },
  {
    "criterion": "Provides a clear and concise explanation of the user's symptoms",
    "axis": "communication_quality",
    "point": 8
  },
  {
    "criterion": "Does not mention the use of unproven or alternative treatments",
    "axis": "accuracy",
    "point": 8
  }
]