[
  {
    "criterion": "Clearly recommends continuing the RICE protocol for a mild ankle sprain with improving symptoms.",
    "points": 8,
    "tags": [
      "level:example",
      "axis:completeness"
    ]
  },
  {
    "criterion": "Specifies the correct duration for ice application (15-20 minutes at a time) for a mild ankle sprain.",
    "points": 7,
    "tags": [
      "level:example",
      "axis:accuracy"
    ]
  },
  {
    "criterion": "Provides specific warning signs for when to seek medical attention for a mild ankle sprain, such as increased pain/swelling, instability, and difficulty bearing weight.",
    "points": 9,
    "tags": [
      "level:example",
      "axis:completeness"
    ]
  },
  {
    "criterion": "Includes guidance on gradual return to activity and ankle strengthening exercises after initial recovery.",
    "points": 5,
    "tags": [
      "level:example",
      "axis:completeness"
    ]
  },
  {
    "criterion": "Recommends an immediate full return to normal activities for this recently injured ankle.",
    "points": -8,
    "tags": [
      "level:example",
      "axis:accuracy"
    ]
  },
  {
    "criterion": "Uses unnatural Turkish medical terminology like \"yerel reaksiyonlar\" instead of \"lokal reaksiyon\" or awkward phrasing such as \"ciltte aşırı soğuma\" when explaining ankle sprain treatment.",
    "points": -4,
    "tags": [
      "level:example",
      "axis:communication_quality"
    ]
  },
  {
    "criterion": "Suggests complete immobilization or avoidance of weight-bearing for a mild ankle sprain.",
    "points": -6,
    "tags": [
      "level:example",
      "axis:accuracy"
    ]
  },
  {
    "criterion": "Contains redundant or repetitive information that dilutes key points about ankle sprain management.",
    "points": -3,
    "tags": [
      "level:example",
      "axis:communication_quality"
    ]
  }
]